CMakeLists.txt
LICENSE
MANIFEST.in
README.md
pyproject.toml
requirements.txt
setup.py
databento_fast.egg-info/PKG-INFO
databento_fast.egg-info/SOURCES.txt
databento_fast.egg-info/dependency_links.txt
databento_fast.egg-info/not-zip-safe
databento_fast.egg-info/requires.txt
databento_fast.egg-info/top_level.txt
include/databento/dbn.hpp
include/databento/parser.hpp
python/databento_py.cpp
python/example_download_and_parse.py
python/example_python.py
python/minimal_example.py
python/simple_download_parse.py
src/parser.cpp