Metadata-Version: 2.4
Name: databento-fast
Version: 1.0.0
Summary: Ultra-fast Databento DBN parser (200M+ records/sec) with C++ and Python
Home-page: https://github.com/rbarfinezhadfeli0/databento-fast
Author: databento-fast contributors
Author-email: 
Project-URL: Bug Tracker, https://github.com/rbarfinezhadfeli0/databento-fast/issues
Project-URL: Documentation, https://github.com/rbarfinezhadfeli0/databento-fast
Project-URL: Source Code, https://github.com/rbarfinezhadfeli0/databento-fast
Keywords: databento market-data high-frequency-trading hft parsing performance cpp fast mbo
Classifier: Development Status :: 4 - Beta
Classifier: Intended Audience :: Developers
Classifier: Intended Audience :: Financial and Insurance Industry
Classifier: Topic :: Software Development :: Libraries :: Python Modules
Classifier: Topic :: Office/Business :: Financial
Classifier: License :: OSI Approved :: MIT License
Classifier: Programming Language :: C++
Classifier: Programming Language :: Python :: 3
Classifier: Programming Language :: Python :: 3.7
Classifier: Programming Language :: Python :: 3.8
Classifier: Programming Language :: Python :: 3.9
Classifier: Programming Language :: Python :: 3.10
Classifier: Programming Language :: Python :: 3.11
Classifier: Programming Language :: Python :: 3.12
Classifier: Operating System :: POSIX :: Linux
Classifier: Operating System :: MacOS
Requires-Python: >=3.7
License-File: LICENSE
Requires-Dist: pybind11>=2.10.0
Provides-Extra: dev
Requires-Dist: pytest; extra == "dev"
Requires-Dist: numpy; extra == "dev"
Requires-Dist: pandas; extra == "dev"
Provides-Extra: databento
Requires-Dist: databento>=0.30.0; extra == "databento"
Dynamic: author
Dynamic: classifier
Dynamic: description
Dynamic: description-content-type
Dynamic: home-page
Dynamic: keywords
Dynamic: license-file
Dynamic: project-url
Dynamic: provides-extra
Dynamic: requires-dist
Dynamic: requires-python
Dynamic: summary
